Workbook

Sheet Sheet2
N2: MON | O2: TUE | P2: WED | Q2: THU | R2: FRI | S2: SAT | T2: SUN | U2: MON | V2: TUE | W2: WED | X2: THU | Y2: FRI | Z2: SAT | AA2: SUN | AB2: MON | AC2: TUE | AD2: WED | AE2: THU | AF2: FRI | AG2: SAT | AH2: SUN | AI2: MON | AJ2: TUE | AK2: WED | AL2: THU | AM2: FRI | AN2: SAT | AO2: SUN | AP2: MON | AQ2: TUE
A3: EMP ID | B3: NAME | C3: DESGINATION | D3: DEPARTMENT | E3: DATE JOINING | F3: MOBILE NO | G3: EMAIL ID | H3: ADHAR NO | I3: PAN NO | J3: IFSC CODE | K3: ACCOUNT NO | L3: EPF NO | M3: ESI NO | N3: 45901 | O3: 45902 | P3: 45903 | Q3: 45904 | R3: 45905 | S3: 45906 | T3: 45907 | U3: 45908 | V3: 45909 | W3: 45910 | X3: 45911 | Y3: 45912 | Z3: 45913 | AA3: 45914 | AB3: 45915 | AC3: 45916 | AD3: 45917 | AE3: 45918 | AF3: 45919 | AG3: 45920 | AH3: 45921 | AI3: 45922 | AJ3: 45923 | AK3: 45924 | AL3: 45925 | AM3: 45926 | AN3: 45927 | AO3: 45928 | AP3: 45929 | AQ3: 45930 | AR3: PRESENT | AS3: ABSENT | AT3: HALFDAY | AU3: LEAVE | AV3: WEEKOFF | AW3: HOLIDAY | AX3: PAYABLE DAYS | AY3: Basic Salary | AZ3: Actual Basic | BA3: DA | BB3: HRA | BC3: TA | BD3: Inentive | BE3: Gross Salary | BF3: EPF 12% | BG3: ESI 0.75% | BH3: EPF 3.67% | BI3: EPS 8.33% | BJ3: ESI 3.25% | BK3: PT | BL3: TDS | BM3: Advance | BN3: Net Salary
A4: EMP001 | B4: Aarav Sharma | C4: Engineer | D4: Marketing | E4: 12-04-2023 | F4: 9723171730 | G4: aarav.sharma@example.com | H4: 408522180226 | I4: TASTI8900S | J4: PUNB0387646 | K4: 517558434033 | L4: MH/3183306 | M4: 43790951306060913 | N4: P | O4: P | P4: P | Q4: P | R4: P | S4: P | T4: WO | U4: P | V4: P | W4: P | X4: P | Y4: P | Z4: P | AA4: WO | AB4: P | AC4: P | AD4: P | AE4: A | AF4: P | AG4: P | AH4: WO | AI4: P | AJ4: P | AK4: P | AL4: P | AM4: P | AN4: P | AO4: WO | AP4: P | AQ4: P | AR4: =COUNTIF(N4:AQ4,"P") -> 25 | AS4: =COUNTIF(N4:AQ4,"A") -> 1 | AT4: =COUNTIF(N4:AQ4,"HO") -> 0 | AU4: =COUNTIF(N4:AQ4,"L") -> 0 | AV4: =COUNTIF(N4:AQ4,"WO") -> 4 | AW4: =COUNTIF(N4:AQ4,"H") -> 0 | AX4: =SUM(AR4:AW4)-AS4-IF(AU4>1,AU4-1,0)-(AT4/2)-AV4 -> 25 | AY4: 15000 | AZ4: =AY4/30*AX4 -> 12500 | BA4: =AZ4*20% -> 2500 | BB4: =AZ4*40% -> 5000 | BC4: =5000/30*AX4 -> 4166.6667 | BD4: =VLOOKUP(A4,[1]Sheet3!$A$2:$D$52,4,0) -> #N/A | BE4: =SUM(AZ4:BD4) -> #N/A | BF4: =IF(SUM(AZ4:BA4)>=15000,1800,SUM(AZ4:BA4)*12%) -> 1800 | BG4: =BE4*0.75% -> #N/A | BH4: =IF(SUM(AZ4:BA4)>=15000,550.5,(SUM(AZ4:BA4)*3.67%)) -> 550.5 | BI4: =IF(SUM(AZ4:BA4)>=15000,1249.5,SUM(AZ4:BA4)*8.33%) -> 1249.5 | BJ4: =IF(BE4>=21000,0,BE4*3.25%) -> #N/A | BK4: =IF(BE4>25000,200,IF(BE4>20000,150,IF(BE4>15000,100,0))) -> #N/A | BL4: =IF((BE4*12)<=400000,0, IF((BE4*12)<=800000,((BE4*12)-400000)*5%, IF((BE4*12)<=1200000,20000+((BE4*12)-800000)*10%, IF((BE4*12)<=1600000,60000+((BE4*12)-1200000)*15%, IF((BE4*12)<=2000000,120000+((BE4*12)-1600000)*20%, IF((BE4*12)<=2400000,200000+((BE4*12)-2000000)*25%, IF((BE4*12)>2400000,300000+((BE4*12)-2400000)*30%)))))))/12 -> #N/A | BM4: 0 | BN4: =BE4-BF4-BG4-BH4-BI4-BJ4-BK4-BL4-BM4 -> #N/A
A5: EMP002 | B5: Vihaan Patel | C5: Analyst | D5: Marketing | E5: 04-06-2019 | F5: 9709598138 | G5: vihaan.patel@example.com | H5: 416148021695 | I5: WCZWQ2953U | J5: HDFC0727281 | K5: 369486504494 | L5: MH/1499603 | M5: 75312326499889147 | N5: A | O5: P | P5: P | Q5: P | R5: P | S5: P | T5: WO | U5: P | V5: P | W5: P | X5: P | Y5: P | Z5: P | AA5: WO | AB5: A | AC5: P | AD5: H | AE5: P | AF5: P | AG5: A | AH5: WO | AI5: P | AJ5: A | AK5: P | AL5: P | AM5: P | AN5: P | AO5: WO | AP5: P | AQ5: P | AR5: =COUNTIF(N5:AQ5,"P") -> 21 | AS5: =COUNTIF(N5:AQ5,"A") -> 4 | AT5: =COUNTIF(N5:AQ5,"HO") -> 0 | AU5: =COUNTIF(N5:AQ5,"L") -> 0 | AV5: =COUNTIF(N5:AQ5,"WO") -> 4 | AW5: =COUNTIF(N5:AQ5,"H") -> 1 | AX5: =SUM(AR5:AW5)-AS5-IF(AU5>1,AU5-1,0)-(AT5/2)-AV5 -> 22 | AY5: 11000 | AZ5: =AY5/30*AX5 -> 8066.6667 | BA5: =AZ5*20% -> 1613.3333 | BB5: =AZ5*40% -> 3226.6667 | BC5: =5000/30*AX5 -> 3666.6667 | BD5: =VLOOKUP(A5,[1]Sheet3!$A$2:$D$52,4,0) -> #N/A | BE5: =SUM(AZ5:BD5) -> #N/A | BF5: =IF(SUM(AZ5:BA5)>=15000,1800,SUM(AZ5:BA5)*12%) -> 1161.6 | BG5: =BE5*0.75% -> #N/A | BH5: =IF(SUM(AZ5:BA5)>=15000,550.5,(SUM(AZ5:BA5)*3.67%)) -> 355.256 | BI5: =IF(SUM(AZ5:BA5)>=15000,1249.5,SUM(AZ5:BA5)*8.33%) -> 806.344 | BJ5: =IF(BE5>=21000,0,BE5*3.25%) -> #N/A | BK5: =IF(BE5>25000,200,IF(BE5>20000,150,IF(BE5>15000,100,0))) -> #N/A | BL5: =IF((BE5*12)<=400000,0, IF((BE5*12)<=800000,((BE5*12)-400000)*5%, IF((BE5*12)<=1200000,20000+((BE5*12)-800000)*10%, IF((BE5*12)<=1600000,60000+((BE5*12)-1200000)*15%, IF((BE5*12)<=2000000,120000+((BE5*12)-1600000)*20%, IF((BE5*12)<=2400000,200000+((BE5*12)-2000000)*25%, IF((BE5*12)>2400000,300000+((BE5*12)-2400000)*30%)))))))/12 -> #N/A | BM5: 0 | BN5: =BE5-BF5-BG5-BH5-BI5-BJ5-BK5-BL5-BM5 -> #N/A
A6: EMP003 | B6: Aditya Rao | C6: Executive | D6: Operations | E6: 02-09-2025 | F6: 9781754517 | G6: aditya.rao@example.com | H6: 268814622037 | I6: MQJQW7509F | J6: KKBK0278540 | K6: 441481637956 | L6: MH/6747422 | M6: 49962259181266537 | N6: P | O6: A | P6: A | Q6: P | R6: P | S6: P | T6: WO | U6: P | V6: P | W6: P | X6: P | Y6: P | Z6: P | AA6: WO | AB6: A | AC6: P | AD6: P | AE6: P | AF6: L | AG6: P | AH6: WO | AI6: P | AJ6: A | AK6: A | AL6: P | AM6: P | AN6: P | AO6: WO | AP6: P | AQ6: P | AR6: =COUNTIF(N6:AQ6,"P") -> 20 | AS6: =COUNTIF(N6:AQ6,"A") -> 5 | AT6: =COUNTIF(N6:AQ6,"HO") -> 0 | AU6: =COUNTIF(N6:AQ6,"L") -> 1 | AV6: =COUNTIF(N6:AQ6,"WO") -> 4 | AW6: =COUNTIF(N6:AQ6,"H") -> 0 | AX6: =SUM(AR6:AW6)-AS6-IF(AU6>1,AU6-1,0)-(AT6/2)-AV6 -> 21 | AY6: 14000 | AZ6: =AY6/30*AX6 -> 9800 | BA6: =AZ6*20% -> 1960 | BB6: =AZ6*40% -> 3920 | BC6: =5000/30*AX6 -> 3500 | BD6: =VLOOKUP(A6,[1]Sheet3!$A$2:$D$52,4,0) -> #N/A | BE6: =SUM(AZ6:BD6) -> #N/A | BF6: =IF(SUM(AZ6:BA6)>=15000,1800,SUM(AZ6:BA6)*12%) -> 1411.2 | BG6: =BE6*0.75% -> #N/A | BH6: =IF(SUM(AZ6:BA6)>=15000,550.5,(SUM(AZ6:BA6)*3.67%)) -> 431.592 | BI6: =IF(SUM(AZ6:BA6)>=15000,1249.5,SUM(AZ6:BA6)*8.33%) -> 979.608 | BJ6: =IF(BE6>=21000,0,BE6*3.25%) -> #N/A | BK6: =IF(BE6>25000,200,IF(BE6>20000,150,IF(BE6>15000,100,0))) -> #N/A | BL6: =IF((BE6*12)<=400000,0, IF((BE6*12)<=800000,((BE6*12)-400000)*5%, IF((BE6*12)<=1200000,20000+((BE6*12)-800000)*10%, IF((BE6*12)<=1600000,60000+((BE6*12)-1200000)*15%, IF((BE6*12)<=2000000,120000+((BE6*12)-1600000)*20%, IF((BE6*12)<=2400000,200000+((BE6*12)-2000000)*25%, IF((BE6*12)>2400000,300000+((BE6*12)-2400000)*30%)))))))/12 -> #N/A | BM6: 0 | BN6: =BE6-BF6-BG6-BH6-BI6-BJ6-BK6-BL6-BM6 -> #N/A
A7: EMP004 | B7: Arjun Mehta | C7: Supervisor | D7: Finance | E7: 12-12-2018 | F7: 9326772684 | G7: arjun.mehta@example.com | H7: 695967863048 | I7: OUXKV3740M | J7: PUNB0047760 | K7: 173444133355 | L7: MH/2879322 | M7: 81497436059586419 | N7: P | O7: P | P7: P | Q7: P | R7: P | S7: P | T7: WO | U7: P | V7: P | W7: L | X7: P | Y7: P | Z7: P | AA7: WO | AB7: A | AC7: P | AD7: H | AE7: P | AF7: P | AG7: P | AH7: WO | AI7: P | AJ7: L | AK7: P | AL7: P | AM7: L | AN7: P | AO7: WO | AP7: P | AQ7: P | AR7: =COUNTIF(N7:AQ7,"P") -> 21 | AS7: =COUNTIF(N7:AQ7,"A") -> 1 | AT7: =COUNTIF(N7:AQ7,"HO") -> 0 | AU7: =COUNTIF(N7:AQ7,"L") -> 3 | AV7: =COUNTIF(N7:AQ7,"WO") -> 4 | AW7: =COUNTIF(N7:AQ7,"H") -> 1 | AX7: =SUM(AR7:AW7)-AS7-IF(AU7>1,AU7-1,0)-(AT7/2)-AV7 -> 23 | AY7: 19000 | AZ7: =AY7/30*AX7 -> 14566.667 | BA7: =AZ7*20% -> 2913.3333 | BB7: =AZ7*40% -> 5826.6667 | BC7: =5000/30*AX7 -> 3833.3333 | BD7: =VLOOKUP(A7,[1]Sheet3!$A$2:$D$52,4,0) -> #N/A | BE7: =SUM(AZ7:BD7) -> #N/A | BF7: =IF(SUM(AZ7:BA7)>=15000,1800,SUM(AZ7:BA7)*12%) -> 1800 | BG7: =BE7*0.75% -> #N/A | BH7: =IF(SUM(AZ7:BA7)>=15000,550.5,(SUM(AZ7:BA7)*3.67%)) -> 550.5 | BI7: =IF(SUM(AZ7:BA7)>=15000,1249.5,SUM(AZ7:BA7)*8.33%) -> 1249.5 | BJ7: =IF(BE7>=21000,0,BE7*3.25%) -> #N/A | BK7: =IF(BE7>25000,200,IF(BE7>20000,150,IF(BE7>15000,100,0))) -> #N/A | BL7: =IF((BE7*12)<=400000,0, IF((BE7*12)<=800000,((BE7*12)-400000)*5%, IF((BE7*12)<=1200000,20000+((BE7*12)-800000)*10%, IF((BE7*12)<=1600000,60000+((BE7*12)-1200000)*15%, IF((BE7*12)<=2000000,120000+((BE7*12)-1600000)*20%, IF((BE7*12)<=2400000,200000+((BE7*12)-2000000)*25%, IF((BE7*12)>2400000,300000+((BE7*12)-2400000)*30%)))))))/12 -> #N/A | BM7: 0 | BN7: =BE7-BF7-BG7-BH7-BI7-BJ7-BK7-BL7-BM7 -> #N/A
A8: EMP005 | B8: Vivaan Reddy | C8: Assistant | D8: Operations | E8: 02-09-2022 | F8: 9651703086 | G8: vivaan.reddy@example.com | H8: 137770197102 | I8: OWCHB1828R | J8: KKBK0204723 | K8: 701133421304 | L8: MH/7166735 | M8: 14648212952090225 | N8: P | O8: P | P8: L | Q8: A | R8: P | S8: P | T8: WO | U8: P | V8: P | W8: P | X8: P | Y8: P | Z8: P | AA8: WO | AB8: P | AC8: A | AD8: P | AE8: L | AF8: P | AG8: L | AH8: WO | AI8: P | AJ8: P | AK8: P | AL8: L | AM8: P | AN8: P | AO8: WO | AP8: P | AQ8: P | AR8: =COUNTIF(N8:AQ8,"P") -> 20 | AS8: =COUNTIF(N8:AQ8,"A") -> 2 | AT8: =COUNTIF(N8:AQ8,"HO") -> 0 | AU8: =COUNTIF(N8:AQ8,"L") -> 4 | AV8: =COUNTIF(N8:AQ8,"WO") -> 4 | AW8: =COUNTIF(N8:AQ8,"H") -> 0 | AX8: =SUM(AR8:AW8)-AS8-IF(AU8>1,AU8-1,0)-(AT8/2)-AV8 -> 21 | AY8: 13000 | AZ8: =AY8/30*AX8 -> 9100 | BA8: =AZ8*20% -> 1820 | BB8: =AZ8*40% -> 3640 | BC8: =5000/30*AX8 -> 3500 | BD8: =VLOOKUP(A8,[1]Sheet3!$A$2:$D$52,4,0) -> #N/A | BE8: =SUM(AZ8:BD8) -> #N/A | BF8: =IF(SUM(AZ8:BA8)>=15000,1800,SUM(AZ8:BA8)*12%) -> 1310.4 | BG8: =BE8*0.75% -> #N/A | BH8: =IF(SUM(AZ8:BA8)>=15000,550.5,(SUM(AZ8:BA8)*3.67%)) -> 400.764 | BI8: =IF(SUM(AZ8:BA8)>=15000,1249.5,SUM(AZ8:BA8)*8.33%) -> 909.636 | BJ8: =IF(BE8>=21000,0,BE8*3.25%) -> #N/A | BK8: =IF(BE8>25000,200,IF(BE8>20000,150,IF(BE8>15000,100,0))) -> #N/A | BL8: =IF((BE8*12)<=400000,0, IF((BE8*12)<=800000,((BE8*12)-400000)*5%, IF((BE8*12)<=1200000,20000+((BE8*12)-800000)*10%, IF((BE8*12)<=1600000,60000+((BE8*12)-1200000)*15%, IF((BE8*12)<=2000000,120000+((BE8*12)-1600000)*20%, IF((BE8*12)<=2400000,200000+((BE8*12)-2000000)*25%, IF((BE8*12)>2400000,300000+((BE8*12)-2400000)*30%)))))))/12 -> #N/A | BM8: 6000 | BN8: =BE8-BF8-BG8-BH8-BI8-BJ8-BK8-BL8-BM8 -> #N/A
A9: EMP006 | B9: Sai Kumar | C9: Engineer | D9: Finance | E9: 17-04-2021 | F9: 9497721474 | G9: sai.kumar@example.com | H9: 390379265872 | I9: YORFR8185H | J9: SBIN0078732 | K9: 815558307439 | L9: MH/1707081 | M9: 35915249757810686 | N9: P | O9: P | P9: P | Q9: P | R9: A | S9: P | T9: WO | U9: P | V9: L | W9: P | X9: P | Y9: L | Z9: P | AA9: WO | AB9: P | AC9: H | AD9: P | AE9: P | AF9: P | AG9: P | AH9: WO | AI9: P | AJ9: P | AK9: P | AL9: P | AM9: L | AN9: A | AO9: WO | AP9: P | AQ9: P | AR9: =COUNTIF(N9:AQ9,"P") -> 20 | AS9: =COUNTIF(N9:AQ9,"A") -> 2 | AT9: =COUNTIF(N9:AQ9,"HO") -> 0 | AU9: =COUNTIF(N9:AQ9,"L") -> 3 | AV9: =COUNTIF(N9:AQ9,"WO") -> 4 | AW9: =COUNTIF(N9:AQ9,"H") -> 1 | AX9: =SUM(AR9:AW9)-AS9-IF(AU9>1,AU9-1,0)-(AT9/2)-AV9 -> 22 | AY9: 14000 | AZ9: =AY9/30*AX9 -> 10266.667 | BA9: =AZ9*20% -> 2053.3333 | BB9: =AZ9*40% -> 4106.6667 | BC9: =5000/30*AX9 -> 3666.6667 | BD9: =VLOOKUP(A9,[1]Sheet3!$A$2:$D$52,4,0) -> #N/A | BE9: =SUM(AZ9:BD9) -> #N/A | BF9: =IF(SUM(AZ9:BA9)>=15000,1800,SUM(AZ9:BA9)*12%) -> 1478.4 | BG9: =BE9*0.75% -> #N/A | BH9: =IF(SUM(AZ9:BA9)>=15000,550.5,(SUM(AZ9:BA9)*3.67%)) -> 452.144 | BI9: =IF(SUM(AZ9:BA9)>=15000,1249.5,SUM(AZ9:BA9)*8.33%) -> 1026.256 | BJ9: =IF(BE9>=21000,0,BE9*3.25%) -> #N/A | BK9: =IF(BE9>25000,200,IF(BE9>20000,150,IF(BE9>15000,100,0))) -> #N/A | BL9: =IF((BE9*12)<=400000,0, IF((BE9*12)<=800000,((BE9*12)-400000)*5%, IF((BE9*12)<=1200000,20000+((BE9*12)-800000)*10%, IF((BE9*12)<=1600000,60000+((BE9*12)-1200000)*15%, IF((BE9*12)<=2000000,120000+((BE9*12)-1600000)*20%, IF((BE9*12)<=2400000,200000+((BE9*12)-2000000)*25%, IF((BE9*12)>2400000,300000+((BE9*12)-2400000)*30%)))))))/12 -> #N/A | BM9: 0 | BN9: =BE9-BF9-BG9-BH9-BI9-BJ9-BK9-BL9-BM9 -> #N/A
A10: EMP007 | B10: Karthik Iyer | C10: Executive | D10: Finance | E10: 21-09-2024 | F10: 9764902682 | G10: karthik.iyer@example.com | H10: 227853632233 | I10: JQZZC7995E | J10: KKBK0610226 | K10: 847423651159 | L10: MH/0583728 | M10: 86443002205391316 | N10: HO | O10: P | P10: L | Q10: P | R10: P | S10: A | T10: WO | U10: P | V10: P | W10: P | X10: P | Y10: P | Z10: P | AA10: WO | AB10: H | AC10: P | AD10: L | AE10: A | AF10: P | AG10: P | AH10: WO | AI10: P | AJ10: L | AK10: P | AL10: P | AM10: P | AN10: P | AO10: WO | AP10: P | AQ10: P | AR10: =COUNTIF(N10:AQ10,"P") -> 19 | AS10: =COUNTIF(N10:AQ10,"A") -> 2 | AT10: =COUNTIF(N10:AQ10,"HO") -> 1 | AU10: =COUNTIF(N10:AQ10,"L") -> 3 | AV10: =COUNTIF(N10:AQ10,"WO") -> 4 | AW10: =COUNTIF(N10:AQ10,"H") -> 1 | AX10: =SUM(AR10:AW10)-AS10-IF(AU10>1,AU10-1,0)-(AT10/2)-AV10 -> 21.5 | AY10: 14000 | AZ10: =AY10/30*AX10 -> 10033.333 | BA10: =AZ10*20% -> 2006.6667 | BB10: =AZ10*40% -> 4013.3333 | BC10: =5000/30*AX10 -> 3583.3333 | BD10: =VLOOKUP(A10,[1]Sheet3!$A$2:$D$52,4,0) -> #N/A | BE10: =SUM(AZ10:BD10) -> #N/A | BF10: =IF(SUM(AZ10:BA10)>=15000,1800,SUM(AZ10:BA10)*12%) -> 1444.8 | BG10: =BE10*0.75% -> #N/A | BH10: =IF(SUM(AZ10:BA10)>=15000,550.5,(SUM(AZ10:BA10)*3.67%)) -> 441.868 | BI10: =IF(SUM(AZ10:BA10)>=15000,1249.5,SUM(AZ10:BA10)*8.33%) -> 1002.932 | BJ10: =IF(BE10>=21000,0,BE10*3.25%) -> #N/A | BK10: =IF(BE10>25000,200,IF(BE10>20000,150,IF(BE10>15000,100,0))) -> #N/A | BL10: =IF((BE10*12)<=400000,0, IF((BE10*12)<=800000,((BE10*12)-400000)*5%, IF((BE10*12)<=1200000,20000+((BE10*12)-800000)*10%, IF((BE10*12)<=1600000,60000+((BE10*12)-1200000)*15%, IF((BE10*12)<=2000000,120000+((BE10*12)-1600000)*20%, IF((BE10*12)<=2400000,200000+((BE10*12)-2000000)*25%, IF((BE10*12)>2400000,300000+((BE10*12)-2400000)*30%)))))))/12 -> #N/A | BM10: 0 | BN10: =BE10-BF10-BG10-BH10-BI10-BJ10-BK10-BL10-BM10 -> #N/A
A11: EMP008 | B11: Rohan Nair | C11: Executive | D11: Marketing | E11: 22-03-2021 | F11: 9751438899 | G11: rohan.nair@example.com | H11: 272711675608 | I11: IGBUP2955P | J11: HDFC0124667 | K11: 736405256594 | L11: MH/3848334 | M11: 24855338425442785 | N11: P | O11: P | P11: P | Q11: P | R11: L | S11: P | T11: WO | U11: L | V11: P | W11: P | X11: P | Y11: P | Z11: P | AA11: WO | AB11: P | AC11: P | AD11: P | AE11: A | AF11: P | AG11: L | AH11: WO | AI11: P | AJ11: P | AK11: P | AL11: P | AM11: P | AN11: P | AO11: WO | AP11: P | AQ11: P | AR11: =COUNTIF(N11:AQ11,"P") -> 22 | AS11: =COUNTIF(N11:AQ11,"A") -> 1 | AT11: =COUNTIF(N11:AQ11,"HO") -> 0 | AU11: =COUNTIF(N11:AQ11,"L") -> 3 | AV11: =COUNTIF(N11:AQ11,"WO") -> 4 | AW11: =COUNTIF(N11:AQ11,"H") -> 0 | AX11: =SUM(AR11:AW11)-AS11-IF(AU11>1,AU11-1,0)-(AT11/2)-AV11 -> 23 | AY11: 15000 | AZ11: =AY11/30*AX11 -> 11500 | BA11: =AZ11*20% -> 2300 | BB11: =AZ11*40% -> 4600 | BC11: =5000/30*AX11 -> 3833.3333 | BD11: =VLOOKUP(A11,[1]Sheet3!$A$2:$D$52,4,0) -> #N/A | BE11: =SUM(AZ11:BD11) -> #N/A | BF11: =IF(SUM(AZ11:BA11)>=15000,1800,SUM(AZ11:BA11)*12%) -> 1656 | BG11: =BE11*0.75% -> #N/A | BH11: =IF(SUM(AZ11:BA11)>=15000,550.5,(SUM(AZ11:BA11)*3.67%)) -> 506.46 | BI11: =IF(SUM(AZ11:BA11)>=15000,1249.5,SUM(AZ11:BA11)*8.33%) -> 1149.54 | BJ11: =IF(BE11>=21000,0,BE11*3.25%) -> #N/A | BK11: =IF(BE11>25000,200,IF(BE11>20000,150,IF(BE11>15000,100,0))) -> #N/A | BL11: =IF((BE11*12)<=400000,0, IF((BE11*12)<=800000,((BE11*12)-400000)*5%, IF((BE11*12)<=1200000,20000+((BE11*12)-800000)*10%, IF((BE11*12)<=1600000,60000+((BE11*12)-1200000)*15%, IF((BE11*12)<=2000000,120000+((BE11*12)-1600000)*20%, IF((BE11*12)<=2400000,200000+((BE11*12)-2000000)*25%, IF((BE11*12)>2400000,300000+((BE11*12)-2400000)*30%)))))))/12 -> #N/A | BM11: 0 | BN11: =BE11-BF11-BG11-BH11-BI11-BJ11-BK11-BL11-BM11 -> #N/A
A12: EMP009 | B12: Krishna Das | C12: Assistant | D12: Finance | E12: 30-08-2021 | F12: 9010451756 | G12: krishna.das@example.com | H12: 210188000274 | I12: TJNVS8878M | J12: PUNB0581791 | K12: 338531694105 | L12: MH/3408089 | M12: 21363270435774555 | N12: HO | O12: P | P12: P | Q12: P | R12: P | S12: L | T12: WO | U12: P | V12: P | W12: A | X12: P | Y12: P | Z12: H | AA12: WO | AB12: P | AC12: P | AD12: P | AE12: A | AF12: P | AG12: P | AH12: WO | AI12: P | AJ12: P | AK12: P | AL12: L | AM12: H | AN12: A | AO12: WO | AP12: P | AQ12: P | AR12: =COUNTIF(N12:AQ12,"P") -> 18 | AS12: =COUNTIF(N12:AQ12,"A") -> 3 | AT12: =COUNTIF(N12:AQ12,"HO") -> 1 | AU12: =COUNTIF(N12:AQ12,"L") -> 2 | AV12: =COUNTIF(N12:AQ12,"WO") -> 4 | AW12: =COUNTIF(N12:AQ12,"H") -> 2 | AX12: =SUM(AR12:AW12)-AS12-IF(AU12>1,AU12-1,0)-(AT12/2)-AV12 -> 21.5 | AY12: 16000 | AZ12: =AY12/30*AX12 -> 11466.667 | BA12: =AZ12*20% -> 2293.3333 | BB12: =AZ12*40% -> 4586.6667 | BC12: =5000/30*AX12 -> 3583.3333 | BD12: =VLOOKUP(A12,[1]Sheet3!$A$2:$D$52,4,0) -> #N/A | BE12: =SUM(AZ12:BD12) -> #N/A | BF12: =IF(SUM(AZ12:BA12)>=15000,1800,SUM(AZ12:BA12)*12%) -> 1651.2 | BG12: =BE12*0.75% -> #N/A | BH12: =IF(SUM(AZ12:BA12)>=15000,550.5,(SUM(AZ12:BA12)*3.67%)) -> 504.992 | BI12: =IF(SUM(AZ12:BA12)>=15000,1249.5,SUM(AZ12:BA12)*8.33%) -> 1146.208 | BJ12: =IF(BE12>=21000,0,BE12*3.25%) -> #N/A | BK12: =IF(BE12>25000,200,IF(BE12>20000,150,IF(BE12>15000,100,0))) -> #N/A | BL12: =IF((BE12*12)<=400000,0, IF((BE12*12)<=800000,((BE12*12)-400000)*5%, IF((BE12*12)<=1200000,20000+((BE12*12)-800000)*10%, IF((BE12*12)<=1600000,60000+((BE12*12)-1200000)*15%, IF((BE12*12)<=2000000,120000+((BE12*12)-1600000)*20%, IF((BE12*12)<=2400000,200000+((BE12*12)-2000000)*25%, IF((BE12*12)>2400000,300000+((BE12*12)-2400000)*30%)))))))/12 -> #N/A | BM12: 0 | BN12: =BE12-BF12-BG12-BH12-BI12-BJ12-BK12-BL12-BM12 -> #N/A
A13: EMP010 | B13: Aniket Joshi | C13: Supervisor | D13: Sales | E13: 28-08-2018 | F13: 9712376781 | G13: aniket.joshi@example.com | H13: 021979116563 | I13: LCXBJ3655W | J13: KKBK0429888 | K13: 732633217326 | L13: MH/6420106 | M13: 03019369349975773 | N13: P | O13: P | P13: P | Q13: P | R13: P | S13: P | T13: WO | U13: L | V13: P | W13: P | X13: A | Y13: L | Z13: P | AA13: WO | AB13: P | AC13: L | AD13: P | AE13: A | AF13: H | AG13: P | AH13: WO | AI13: P | AJ13: L | AK13: P | AL13: P | AM13: H | AN13: P | AO13: WO | AP13: P | AQ13: P | AR13: =COUNTIF(N13:AQ13,"P") -> 18 | AS13: =COUNTIF(N13:AQ13,"A") -> 2 | AT13: =COUNTIF(N13:AQ13,"HO") -> 0 | AU13: =COUNTIF(N13:AQ13,"L") -> 4 | AV13: =COUNTIF(N13:AQ13,"WO") -> 4 | AW13: =COUNTIF(N13:AQ13,"H") -> 2 | AX13: =SUM(AR13:AW13)-AS13-IF(AU13>1,AU13-1,0)-(AT13/2)-AV13 -> 21 | AY13: 13000 | AZ13: =AY13/30*AX13 -> 9100 | BA13: =AZ13*20% -> 1820 | BB13: =AZ13*40% -> 3640 | BC13: =5000/30*AX13 -> 3500 | BD13: =VLOOKUP(A13,[1]Sheet3!$A$2:$D$52,4,0) -> #N/A | BE13: =SUM(AZ13:BD13) -> #N/A | BF13: =IF(SUM(AZ13:BA13)>=15000,1800,SUM(AZ13:BA13)*12%) -> 1310.4 | BG13: =BE13*0.75% -> #N/A | BH13: =IF(SUM(AZ13:BA13)>=15000,550.5,(SUM(AZ13:BA13)*3.67%)) -> 400.764 | BI13: =IF(SUM(AZ13:BA13)>=15000,1249.5,SUM(AZ13:BA13)*8.33%) -> 909.636 | BJ13: =IF(BE13>=21000,0,BE13*3.25%) -> #N/A | BK13: =IF(BE13>25000,200,IF(BE13>20000,150,IF(BE13>15000,100,0))) -> #N/A | BL13: =IF((BE13*12)<=400000,0, IF((BE13*12)<=800000,((BE13*12)-400000)*5%, IF((BE13*12)<=1200000,20000+((BE13*12)-800000)*10%, IF((BE13*12)<=1600000,60000+((BE13*12)-1200000)*15%, IF((BE13*12)<=2000000,120000+((BE13*12)-1600000)*20%, IF((BE13*12)<=2400000,200000+((BE13*12)-2000000)*25%, IF((BE13*12)>2400000,300000+((BE13*12)-2400000)*30%)))))))/12 -> #N/A | BM13: 0 | BN13: =BE13-BF13-BG13-BH13-BI13-BJ13-BK13-BL13-BM13 -> #N/A
A14: EMP011 | B14: Neha Singh | C14: Analyst | D14: Marketing | E14: 07-08-2019 | F14: 9918390210 | G14: neha.singh@example.com | H14: 967456937554 | I14: FZSJV7868A | J14: KKBK0630583 | K14: 514801721962 | L14: MH/4360317 | M14: 54526218679722972 | N14: HO | O14: P | P14: P | Q14: P | R14: P | S14: P | T14: WO | U14: P | V14: P | W14: P | X14: P | Y14: A | Z14: P | AA14: WO | AB14: P | AC14: P | AD14: P | AE14: H | AF14: H | AG14: L | AH14: WO | AI14: P | AJ14: P | AK14: P | AL14: P | AM14: P | AN14: A | AO14: WO | AP14: H | AQ14: H | AR14: =COUNTIF(N14:AQ14,"P") -> 18 | AS14: =COUNTIF(N14:AQ14,"A") -> 2 | AT14: =COUNTIF(N14:AQ14,"HO") -> 1 | AU14: =COUNTIF(N14:AQ14,"L") -> 1 | AV14: =COUNTIF(N14:AQ14,"WO") -> 4 | AW14: =COUNTIF(N14:AQ14,"H") -> 4 | AX14: =SUM(AR14:AW14)-AS14-IF(AU14>1,AU14-1,0)-(AT14/2)-AV14 -> 23.5 | AY14: 16000 | AZ14: =AY14/30*AX14 -> 12533.333 | BA14: =AZ14*20% -> 2506.6667 | BB14: =AZ14*40% -> 5013.3333 | BC14: =5000/30*AX14 -> 3916.6667 | BD14: =VLOOKUP(A14,[1]Sheet3!$A$2:$D$52,4,0) -> #N/A | BE14: =SUM(AZ14:BD14) -> #N/A | BF14: =IF(SUM(AZ14:BA14)>=15000,1800,SUM(AZ14:BA14)*12%) -> 1800 | BG14: =BE14*0.75% -> #N/A | BH14: =IF(SUM(AZ14:BA14)>=15000,550.5,(SUM(AZ14:BA14)*3.67%)) -> 550.5 | BI14: =IF(SUM(AZ14:BA14)>=15000,1249.5,SUM(AZ14:BA14)*8.33%) -> 1249.5 | BJ14: =IF(BE14>=21000,0,BE14*3.25%) -> #N/A | BK14: =IF(BE14>25000,200,IF(BE14>20000,150,IF(BE14>15000,100,0))) -> #N/A | BL14: =IF((BE14*12)<=400000,0, IF((BE14*12)<=800000,((BE14*12)-400000)*5%, IF((BE14*12)<=1200000,20000+((BE14*12)-800000)*10%, IF((BE14*12)<=1600000,60000+((BE14*12)-1200000)*15%, IF((BE14*12)<=2000000,120000+((BE14*12)-1600000)*20%, IF((BE14*12)<=2400000,200000+((BE14*12)-2000000)*25%, IF((BE14*12)>2400000,300000+((BE14*12)-2400000)*30%)))))))/12 -> #N/A | BM14: 0 | BN14: =BE14-BF14-BG14-BH14-BI14-BJ14-BK14-BL14-BM14 -> #N/A
A15: EMP012 | B15: Priya Sharma | C15: Supervisor | D15: Marketing | E15: 18-04-2021 | F15: 9574249891 | G15: priya.sharma@example.com | H15: 246800101376 | I15: NPUHS4261I | J15: SBIN0088914 | K15: 345239272146 | L15: MH/7907963 | M15: 74750012127326244 | N15: HO | O15: P | P15: P | Q15: P | R15: P | S15: P | T15: WO | U15: P | V15: P | W15: P | X15: P | Y15: H | Z15: A | AA15: WO | AB15: P | AC15: P | AD15: P | AE15: A | AF15: P | AG15: P | AH15: WO | AI15: P | AJ15: P | AK15: P | AL15: P | AM15: A | AN15: P | AO15: WO | AP15: H | AQ15: P | AR15: =COUNTIF(N15:AQ15,"P") -> 20 | AS15: =COUNTIF(N15:AQ15,"A") -> 3 | AT15: =COUNTIF(N15:AQ15,"HO") -> 1 | AU15: =COUNTIF(N15:AQ15,"L") -> 0 | AV15: =COUNTIF(N15:AQ15,"WO") -> 4 | AW15: =COUNTIF(N15:AQ15,"H") -> 2 | AX15: =SUM(AR15:AW15)-AS15-IF(AU15>1,AU15-1,0)-(AT15/2)-AV15 -> 22.5 | AY15: 29000 | AZ15: =AY15/30*AX15 -> 21750 | BA15: =AZ15*20% -> 4350 | BB15: =AZ15*40% -> 8700 | BC15: =5000/30*AX15 -> 3750 | BD15: =VLOOKUP(A15,[1]Sheet3!$A$2:$D$52,4,0) -> #N/A | BE15: =SUM(AZ15:BD15) -> #N/A | BF15: =IF(SUM(AZ15:BA15)>=15000,1800,SUM(AZ15:BA15)*12%) -> 1800 | BG15: =BE15*0.75% -> #N/A | BH15: =IF(SUM(AZ15:BA15)>=15000,550.5,(SUM(AZ15:BA15)*3.67%)) -> 550.5 | BI15: =IF(SUM(AZ15:BA15)>=15000,1249.5,SUM(AZ15:BA15)*8.33%) -> 1249.5 | BJ15: =IF(BE15>=21000,0,BE15*3.25%) -> #N/A | BK15: =IF(BE15>25000,200,IF(BE15>20000,150,IF(BE15>15000,100,0))) -> #N/A | BL15: =IF((BE15*12)<=400000,0, IF((BE15*12)<=800000,((BE15*12)-400000)*5%, IF((BE15*12)<=1200000,20000+((BE15*12)-800000)*10%, IF((BE15*12)<=1600000,60000+((BE15*12)-1200000)*15%, IF((BE15*12)<=2000000,120000+((BE15*12)-1600000)*20%, IF((BE15*12)<=2400000,200000+((BE15*12)-2000000)*25%, IF((BE15*12)>2400000,300000+((BE15*12)-2400000)*30%)))))))/12 -> #N/A | BM15: 0 | BN15: =BE15-BF15-BG15-BH15-BI15-BJ15-BK15-BL15-BM15 -> #N/A
... A26: EMP023 | B26: Manish Kumar | C26: Clerk | D26: Operations | E26: 28-05-2019 | F26: 9234789800 | G26: manish.kumar@example.com | H26: 146633115257 | I26: UBIGI4978Z | J26: HDFC0421869 | K26: 202269171735 | L26: MH/2177264 | M26: 26150763695205817 | N26: P | O26: P | P26: P | Q26: P | R26: H | S26: H | T26: WO | U26: P | V26: P | W26: P | X26: P | Y26: P | Z26: H | AA26: WO | AB26: P | AC26: P | AD26: P | AE26: P | AF26: P | AG26: P | AH26: WO | AI26: P | AJ26: P | AK26: P | AL26: P | AM26: P | AN26: P | AO26: WO | AP26: A | AQ26: P | AR26: =COUNTIF(N26:AQ26,"P") -> 22 | AS26: =COUNTIF(N26:AQ26,"A") -> 1 | AT26: =COUNTIF(N26:AQ26,"HO") -> 0 | AU26: =COUNTIF(N26:AQ26,"L") -> 0 | AV26: =COUNTIF(N26:AQ26,"WO") -> 4 | AW26: =COUNTIF(N26:AQ26,"H") -> 3 | AX26: =SUM(AR26:AW26)-AS26-IF(AU26>1,AU26-1,0)-(AT26/2)-AV26 -> 25 | AY26: 14000 | AZ26: =AY26/30*AX26 -> 11666.667 | BA26: =AZ26*20% -> 2333.3333 | BB26: =AZ26*40% -> 4666.6667 | BC26: =5000/30*AX26 -> 4166.6667 | BD26: =VLOOKUP(A26,[1]Sheet3!$A$2:$D$52,4,0) -> #N/A | BE26: =SUM(AZ26:BD26) -> #N/A | BF26: =IF(SUM(AZ26:BA26)>=15000,1800,SUM(AZ26:BA26)*12%) -> 1680 | BG26: =BE26*0.75% -> #N/A | BH26: =IF(SUM(AZ26:BA26)>=15000,550.5,(SUM(AZ26:BA26)*3.67%)) -> 513.8 | BI26: =IF(SUM(AZ26:BA26)>=15000,1249.5,SUM(AZ26:BA26)*8.33%) -> 1166.2 | BJ26: =IF(BE26>=21000,0,BE26*3.25%) -> #N/A | BK26: =IF(BE26>25000,200,IF(BE26>20000,150,IF(BE26>15000,100,0))) -> #N/A | BL26: =IF((BE26*12)<=400000,0, IF((BE26*12)<=800000,((BE26*12)-400000)*5%, IF((BE26*12)<=1200000,20000+((BE26*12)-800000)*10%, IF((BE26*12)<=1600000,60000+((BE26*12)-1200000)*15%, IF((BE26*12)<=2000000,120000+((BE26*12)-1600000)*20%, IF((BE26*12)<=2400000,200000+((BE26*12)-2000000)*25%, IF((BE26*12)>2400000,300000+((BE26*12)-2400000)*30%)))))))/12 -> #N/A | BM26: 0 | BN26: =BE26-BF26-BG26-BH26-BI26-BJ26-BK26-BL26-BM26 -> #N/A
A27: EMP024 | B27: Vikas Yadav | C27: Engineer | D27: Finance | E27: 19-05-2018 | F27: 9560075698 | G27: vikas.yadav@example.com | H27: 302920069189 | I27: MHCON7536D | J27: HDFC0773316 | K27: 084884613641 | L27: MH/7837142 | M27: 87809633588061028 | N27: P | O27: P | P27: P | Q27: P | R27: H | S27: H | T27: WO | U27: P | V27: P | W27: P | X27: P | Y27: H | Z27: P | AA27: WO | AB27: P | AC27: P | AD27: P | AE27: P | AF27: P | AG27: P | AH27: WO | AI27: P | AJ27: P | AK27: P | AM27: P | AN27: A | AO27: WO | AP27: P | AQ27: P | AR27: =COUNTIF(N27:AQ27,"P") -> 21 | AS27: =COUNTIF(N27:AQ27,"A") -> 1 | AT27: =COUNTIF(N27:AQ27,"HO") -> 0 | AU27: =COUNTIF(N27:AQ27,"L") -> 0 | AV27: =COUNTIF(N27:AQ27,"WO") -> 4 | AW27: =COUNTIF(N27:AQ27,"H") -> 3 | AX27: =SUM(AR27:AW27)-AS27-IF(AU27>1,AU27-1,0)-(AT27/2)-AV27 -> 24 | AY27: 19000 | AZ27: =AY27/30*AX27 -> 15200 | BA27: =AZ27*20% -> 3040 | BB27: =AZ27*40% -> 6080 | BC27: =5000/30*AX27 -> 4000 | BD27: =VLOOKUP(A27,[1]Sheet3!$A$2:$D$52,4,0) -> #N/A | BE27: =SUM(AZ27:BD27) -> #N/A | BF27: =IF(SUM(AZ27:BA27)>=15000,1800,SUM(AZ27:BA27)*12%) -> 1800 | BG27: =BE27*0.75% -> #N/A | BH27: =IF(SUM(AZ27:BA27)>=15000,550.5,(SUM(AZ27:BA27)*3.67%)) -> 550.5 | BI27: =IF(SUM(AZ27:BA27)>=15000,1249.5,SUM(AZ27:BA27)*8.33%) -> 1249.5 | BJ27: =IF(BE27>=21000,0,BE27*3.25%) -> #N/A | BK27: =IF(BE27>25000,200,IF(BE27>20000,150,IF(BE27>15000,100,0))) -> #N/A | BL27: =IF((BE27*12)<=400000,0, IF((BE27*12)<=800000,((BE27*12)-400000)*5%, IF((BE27*12)<=1200000,20000+((BE27*12)-800000)*10%, IF((BE27*12)<=1600000,60000+((BE27*12)-1200000)*15%, IF((BE27*12)<=2000000,120000+((BE27*12)-1600000)*20%, IF((BE27*12)<=2400000,200000+((BE27*12)-2000000)*25%, IF((BE27*12)>2400000,300000+((BE27*12)-2400000)*30%)))))))/12 -> #N/A | BM27: 0 | BN27: =BE27-BF27-BG27-BH27-BI27-BJ27-BK27-BL27-BM27 -> #N/A
A28: EMP025 | B28: Deepak Patel | C28: Assistant | D28: Sales | E28: 13-02-2019 | F28: 9495787931 | G28: deepak.patel@example.com | H28: 585772711775 | I28: TLVRR7322L | J28: PUNB0535895 | K28: 447323931682 | L28: MH/1860133 | M28: 27708188862844661 | N28: HO | O28: P | P28: P | Q28: P | R28: H | S28: P | T28: WO | U28: P | V28: P | W28: P | X28: P | Y28: P | Z28: P | AA28: WO | AB28: P | AC28: P | AD28: P | AE28: P | AF28: P | AG28: P | AH28: WO | AI28: P | AJ28: P | AK28: H | AL28: P | AM28: A | AN28: P | AO28: WO | AP28: P | AQ28: P | AR28: =COUNTIF(N28:AQ28,"P") -> 22 | AS28: =COUNTIF(N28:AQ28,"A") -> 1 | AT28: =COUNTIF(N28:AQ28,"HO") -> 1 | AU28: =COUNTIF(N28:AQ28,"L") -> 0 | AV28: =COUNTIF(N28:AQ28,"WO") -> 4 | AW28: =COUNTIF(N28:AQ28,"H") -> 2 | AX28: =SUM(AR28:AW28)-AS28-IF(AU28>1,AU28-1,0)-(AT28/2)-AV28 -> 24.5 | AY28: 13000 | AZ28: =AY28/30*AX28 -> 10616.667 | BA28: =AZ28*20% -> 2123.3333 | BB28: =AZ28*40% -> 4246.6667 | BC28: =5000/30*AX28 -> 4083.3333 | BD28: =VLOOKUP(A28,[1]Sheet3!$A$2:$D$52,4,0) -> #N/A | BE28: =SUM(AZ28:BD28) -> #N/A | BF28: =IF(SUM(AZ28:BA28)>=15000,1800,SUM(AZ28:BA28)*12%) -> 1528.8 | BG28: =BE28*0.75% -> #N/A | BH28: =IF(SUM(AZ28:BA28)>=15000,550.5,(SUM(AZ28:BA28)*3.67%)) -> 467.558 | BI28: =IF(SUM(AZ28:BA28)>=15000,1249.5,SUM(AZ28:BA28)*8.33%) -> 1061.242 | BJ28: =IF(BE28>=21000,0,BE28*3.25%) -> #N/A | BK28: =IF(BE28>25000,200,IF(BE28>20000,150,IF(BE28>15000,100,0))) -> #N/A | BL28: =IF((BE28*12)<=400000,0, IF((BE28*12)<=800000,((BE28*12)-400000)*5%, IF((BE28*12)<=1200000,20000+((BE28*12)-800000)*10%, IF((BE28*12)<=1600000,60000+((BE28*12)-1200000)*15%, IF((BE28*12)<=2000000,120000+((BE28*12)-1600000)*20%, IF((BE28*12)<=2400000,200000+((BE28*12)-2000000)*25%, IF((BE28*12)>2400000,300000+((BE28*12)-2400000)*30%)))))))/12 -> #N/A | BM28: 0 | BN28: =BE28-BF28-BG28-BH28-BI28-BJ28-BK28-BL28-BM28 -> #N/A
A29: EMP026 | B29: Akash Mehra | C29: Supervisor | D29: HR | E29: 11-11-2017 | F29: 9123905663 | G29: akash.mehra@example.com | H29: 548286068106 | I29: SWTBM5996C | J29: HDFC0388352 | K29: 727772246219 | L29: MH/4052343 | M29: 36311721858369280 | N29: P | O29: P | P29: P | Q29: P | R29: H | S29: H | T29: WO | U29: P | V29: H | W29: H | X29: H | Y29: P | Z29: P | AA29: WO | AB29: P | AC29: P | AD29: P | AE29: P | AF29: P | AG29: P | AH29: WO | AI29: P | AJ29: P | AK29: P | AL29: A | AM29: P | AN29: P | AO29: WO | AP29: P | AQ29: P | AR29: =COUNTIF(N29:AQ29,"P") -> 20 | AS29: =COUNTIF(N29:AQ29,"A") -> 1 | AT29: =COUNTIF(N29:AQ29,"HO") -> 0 | AU29: =COUNTIF(N29:AQ29,"L") -> 0 | AV29: =COUNTIF(N29:AQ29,"WO") -> 4 | AW29: =COUNTIF(N29:AQ29,"H") -> 5 | AX29: =SUM(AR29:AW29)-AS29-IF(AU29>1,AU29-1,0)-(AT29/2)-AV29 -> 25 | AY29: 14000 | AZ29: =AY29/30*AX29 -> 11666.667 | BA29: =AZ29*20% -> 2333.3333 | BB29: =AZ29*40% -> 4666.6667 | BC29: =5000/30*AX29 -> 4166.6667 | BD29: =VLOOKUP(A29,[1]Sheet3!$A$2:$D$52,4,0) -> #N/A | BE29: =SUM(AZ29:BD29) -> #N/A | BF29: =IF(SUM(AZ29:BA29)>=15000,1800,SUM(AZ29:BA29)*12%) -> 1680 | BG29: =BE29*0.75% -> #N/A | BH29: =IF(SUM(AZ29:BA29)>=15000,550.5,(SUM(AZ29:BA29)*3.67%)) -> 513.8 | BI29: =IF(SUM(AZ29:BA29)>=15000,1249.5,SUM(AZ29:BA29)*8.33%) -> 1166.2 | BJ29: =IF(BE29>=21000,0,BE29*3.25%) -> #N/A | BK29: =IF(BE29>25000,200,IF(BE29>20000,150,IF(BE29>15000,100,0))) -> #N/A | BL29: =IF((BE29*12)<=400000,0, IF((BE29*12)<=800000,((BE29*12)-400000)*5%, IF((BE29*12)<=1200000,20000+((BE29*12)-800000)*10%, IF((BE29*12)<=1600000,60000+((BE29*12)-1200000)*15%, IF((BE29*12)<=2000000,120000+((BE29*12)-1600000)*20%, IF((BE29*12)<=2400000,200000+((BE29*12)-2000000)*25%, IF((BE29*12)>2400000,300000+((BE29*12)-2400000)*30%)))))))/12 -> #N/A | BM29: 7000 | BN29: =BE29-BF29-BG29-BH29-BI29-BJ29-BK29-BL29-BM29 -> #N/A
A30: EMP027 | B30: Nitin Agarwal | C30: Assistant | D30: Operations | E30: 05-10-2015 | F30: 9030196539 | G30: nitin.agarwal@example.com | H30: 054804532725 | I30: ELZMQ5201Q | J30: HDFC0933725 | K30: 504106437267 | L30: MH/2506207 | M30: 00124270656385648 | N30: P | O30: P | P30: P | Q30: P | R30: P | S30: P | T30: WO | U30: P | V30: P | W30: P | X30: P | Y30: P | Z30: P | AA30: WO | AB30: P | AC30: P | AD30: P | AE30: P | AF30: P | AG30: P | AH30: WO | AI30: P | AJ30: P | AK30: P | AL30: P | AM30: P | AN30: P | AO30: WO | AP30: P | AQ30: P | AR30: =COUNTIF(N30:AQ30,"P") -> 26 | AS30: =COUNTIF(N30:AQ30,"A") -> 0 | AT30: =COUNTIF(N30:AQ30,"HO") -> 0 | AU30: =COUNTIF(N30:AQ30,"L") -> 0 | AV30: =COUNTIF(N30:AQ30,"WO") -> 4 | AW30: =COUNTIF(N30:AQ30,"H") -> 0 | AX30: =SUM(AR30:AW30)-AS30-IF(AU30>1,AU30-1,0)-(AT30/2)-AV30 -> 26 | AY30: 14000 | AZ30: =AY30/30*AX30 -> 12133.333 | BA30: =AZ30*20% -> 2426.6667 | BB30: =AZ30*40% -> 4853.3333 | BC30: =5000/30*AX30 -> 4333.3333 | BD30: =VLOOKUP(A30,[1]Sheet3!$A$2:$D$52,4,0) -> #N/A | BE30: =SUM(AZ30:BD30) -> #N/A | BF30: =IF(SUM(AZ30:BA30)>=15000,1800,SUM(AZ30:BA30)*12%) -> 1747.2 | BG30: =BE30*0.75% -> #N/A | BH30: =IF(SUM(AZ30:BA30)>=15000,550.5,(SUM(AZ30:BA30)*3.67%)) -> 534.352 | BI30: =IF(SUM(AZ30:BA30)>=15000,1249.5,SUM(AZ30:BA30)*8.33%) -> 1212.848 | BJ30: =IF(BE30>=21000,0,BE30*3.25%) -> #N/A | BK30: =IF(BE30>25000,200,IF(BE30>20000,150,IF(BE30>15000,100,0))) -> #N/A | BL30: =IF((BE30*12)<=400000,0, IF((BE30*12)<=800000,((BE30*12)-400000)*5%, IF((BE30*12)<=1200000,20000+((BE30*12)-800000)*10%, IF((BE30*12)<=1600000,60000+((BE30*12)-1200000)*15%, IF((BE30*12)<=2000000,120000+((BE30*12)-1600000)*20%, IF((BE30*12)<=2400000,200000+((BE30*12)-2000000)*25%, IF((BE30*12)>2400000,300000+((BE30*12)-2400000)*30%)))))))/12 -> #N/A | BM30: 0 | BN30: =BE30-BF30-BG30-BH30-BI30-BJ30-BK30-BL30-BM30 -> #N/A
A31: EMP028 | B31: Harsh Malhotra | C31: Executive | D31: Operations | E31: 28-01-2022 | F31: 9861103171 | G31: harsh.malhotra@example.com | H31: 518955777626 | I31: XWJGI6757D | J31: PUNB0120132 | K31: 593390051724 | L31: MH/8652780 | M31: 01757724225148774 | N31: P | O31: P | P31: P | Q31: P | R31: P | S31: P | T31: WO | U31: P | V31: P | W31: P | X31: P | Y31: P | Z31: P | AA31: WO | AB31: P | AC31: P | AD31: P | AE31: P | AF31: P | AG31: P | AH31: WO | AI31: P | AJ31: A | AK31: P | AL31: P | AM31: P | AN31: P | AO31: WO | AP31: P | AQ31: P | AR31: =COUNTIF(N31:AQ31,"P") -> 25 | AS31: =COUNTIF(N31:AQ31,"A") -> 1 | AT31: =COUNTIF(N31:AQ31,"HO") -> 0 | AU31: =COUNTIF(N31:AQ31,"L") -> 0 | AV31: =COUNTIF(N31:AQ31,"WO") -> 4 | AW31: =COUNTIF(N31:AQ31,"H") -> 0 | AX31: =SUM(AR31:AW31)-AS31-IF(AU31>1,AU31-1,0)-(AT31/2)-AV31 -> 25 | AY31: 15000 | AZ31: =AY31/30*AX31 -> 12500 | BA31: =AZ31*20% -> 2500 | BB31: =AZ31*40% -> 5000 | BC31: =5000/30*AX31 -> 4166.6667 | BD31: =VLOOKUP(A31,[1]Sheet3!$A$2:$D$52,4,0) -> #N/A | BE31: =SUM(AZ31:BD31) -> #N/A | BF31: =IF(SUM(AZ31:BA31)>=15000,1800,SUM(AZ31:BA31)*12%) -> 1800 | BG31: =BE31*0.75% -> #N/A | BH31: =IF(SUM(AZ31:BA31)>=15000,550.5,(SUM(AZ31:BA31)*3.67%)) -> 550.5 | BI31: =IF(SUM(AZ31:BA31)>=15000,1249.5,SUM(AZ31:BA31)*8.33%) -> 1249.5 | BJ31: =IF(BE31>=21000,0,BE31*3.25%) -> #N/A | BK31: =IF(BE31>25000,200,IF(BE31>20000,150,IF(BE31>15000,100,0))) -> #N/A | BL31: =IF((BE31*12)<=400000,0, IF((BE31*12)<=800000,((BE31*12)-400000)*5%, IF((BE31*12)<=1200000,20000+((BE31*12)-800000)*10%, IF((BE31*12)<=1600000,60000+((BE31*12)-1200000)*15%, IF((BE31*12)<=2000000,120000+((BE31*12)-1600000)*20%, IF((BE31*12)<=2400000,200000+((BE31*12)-2000000)*25%, IF((BE31*12)>2400000,300000+((BE31*12)-2400000)*30%)))))))/12 -> #N/A | BM31: 0 | BN31: =BE31-BF31-BG31-BH31-BI31-BJ31-BK31-BL31-BM31 -> #N/A
A32: EMP029 | B32: Ravi Menon | C32: Analyst | D32: Operations | E32: 24-03-2023 | F32: 9681349444 | G32: ravi.menon@example.com | H32: 945428229505 | I32: BQDNC8009Y | J32: SBIN0121080 | K32: 459517276275 | L32: MH/7649764 | M32: 76485264235928409 | N32: P | O32: P | P32: P | Q32: P | R32: P | S32: P | T32: WO | U32: P | V32: P | W32: P | X32: P | Y32: P | Z32: P | AA32: WO | AB32: P | AC32: P | AD32: P | AE32: P | AF32: P | AG32: P | AH32: WO | AI32: P | AJ32: A | AK32: P | AL32: P | AM32: P | AN32: P | AO32: WO | AP32: P | AQ32: P | AR32: =COUNTIF(N32:AQ32,"P") -> 25 | AS32: =COUNTIF(N32:AQ32,"A") -> 1 | AT32: =COUNTIF(N32:AQ32,"HO") -> 0 | AU32: =COUNTIF(N32:AQ32,"L") -> 0 | AV32: =COUNTIF(N32:AQ32,"WO") -> 4 | AW32: =COUNTIF(N32:AQ32,"H") -> 0 | AX32: =SUM(AR32:AW32)-AS32-IF(AU32>1,AU32-1,0)-(AT32/2)-AV32 -> 25 | AY32: 16000 | AZ32: =AY32/30*AX32 -> 13333.333 | BA32: =AZ32*20% -> 2666.6667 | BB32: =AZ32*40% -> 5333.3333 | BC32: =5000/30*AX32 -> 4166.6667 | BD32: =VLOOKUP(A32,[1]Sheet3!$A$2:$D$52,4,0) -> #N/A | BE32: =SUM(AZ32:BD32) -> #N/A | BF32: =IF(SUM(AZ32:BA32)>=15000,1800,SUM(AZ32:BA32)*12%) -> 1800 | BG32: =BE32*0.75% -> #N/A | BH32: =IF(SUM(AZ32:BA32)>=15000,550.5,(SUM(AZ32:BA32)*3.67%)) -> 550.5 | BI32: =IF(SUM(AZ32:BA32)>=15000,1249.5,SUM(AZ32:BA32)*8.33%) -> 1249.5 | BJ32: =IF(BE32>=21000,0,BE32*3.25%) -> #N/A | BK32: =IF(BE32>25000,200,IF(BE32>20000,150,IF(BE32>15000,100,0))) -> #N/A | BL32: =IF((BE32*12)<=400000,0, IF((BE32*12)<=800000,((BE32*12)-400000)*5%, IF((BE32*12)<=1200000,20000+((BE32*12)-800000)*10%, IF((BE32*12)<=1600000,60000+((BE32*12)-1200000)*15%, IF((BE32*12)<=2000000,120000+((BE32*12)-1600000)*20%, IF((BE32*12)<=2400000,200000+((BE32*12)-2000000)*25%, IF((BE32*12)>2400000,300000+((BE32*12)-2400000)*30%)))))))/12 -> #N/A | BM32: 5000 | BN32: =BE32-BF32-BG32-BH32-BI32-BJ32-BK32-BL32-BM32 -> #N/A
A33: EMP030 | B33: Amit Bansal | C33: Supervisor | D33: Finance | E33: 02-01-2020 | F33: 9436232061 | G33: amit.bansal@example.com | H33: 200064094941 | I33: DBIWD3826K | J33: PUNB0541689 | K33: 170297483915 | L33: MH/4811621 | M33: 85582466046553549 | N33: P | O33: P | P33: P | Q33: P | R33: P | S33: P | T33: WO | U33: P | V33: P | W33: P | X33: P | Y33: P | Z33: P | AA33: WO | AB33: P | AC33: P | AD33: P | AE33: P | AF33: P | AG33: P | AH33: WO | AI33: P | AJ33: P | AK33: A | AL33: P | AM33: P | AN33: P | AO33: WO | AP33: P | AQ33: P | AR33: =COUNTIF(N33:AQ33,"P") -> 25 | AS33: =COUNTIF(N33:AQ33,"A") -> 1 | AT33: =COUNTIF(N33:AQ33,"HO") -> 0 | AU33: =COUNTIF(N33:AQ33,"L") -> 0 | AV33: =COUNTIF(N33:AQ33,"WO") -> 4 | AW33: =COUNTIF(N33:AQ33,"H") -> 0 | AX33: =SUM(AR33:AW33)-AS33-IF(AU33>1,AU33-1,0)-(AT33/2)-AV33 -> 25 | AY33: 13000 | AZ33: =AY33/30*AX33 -> 10833.333 | BA33: =AZ33*20% -> 2166.6667 | BB33: =AZ33*40% -> 4333.3333 | BC33: =5000/30*AX33 -> 4166.6667 | BD33: =VLOOKUP(A33,[1]Sheet3!$A$2:$D$52,4,0) -> #N/A | BE33: =SUM(AZ33:BD33) -> #N/A | BF33: =IF(SUM(AZ33:BA33)>=15000,1800,SUM(AZ33:BA33)*12%) -> 1560 | BG33: =BE33*0.75% -> #N/A | BH33: =IF(SUM(AZ33:BA33)>=15000,550.5,(SUM(AZ33:BA33)*3.67%)) -> 477.1 | BI33: =IF(SUM(AZ33:BA33)>=15000,1249.5,SUM(AZ33:BA33)*8.33%) -> 1082.9 | BJ33: =IF(BE33>=21000,0,BE33*3.25%) -> #N/A | BK33: =IF(BE33>25000,200,IF(BE33>20000,150,IF(BE33>15000,100,0))) -> #N/A | BL33: =IF((BE33*12)<=400000,0, IF((BE33*12)<=800000,((BE33*12)-400000)*5%, IF((BE33*12)<=1200000,20000+((BE33*12)-800000)*10%, IF((BE33*12)<=1600000,60000+((BE33*12)-1200000)*15%, IF((BE33*12)<=2000000,120000+((BE33*12)-1600000)*20%, IF((BE33*12)<=2400000,200000+((BE33*12)-2000000)*25%, IF((BE33*12)>2400000,300000+((BE33*12)-2400000)*30%)))))))/12 -> #N/A | BM33: 0 | BN33: =BE33-BF33-BG33-BH33-BI33-BJ33-BK33-BL33-BM33 -> #N/A
A34: EMP031 | B34: Suresh Iyer | C34: Supervisor | D34: Finance | E34: 14-04-2018 | F34: 9738982357 | G34: suresh.iyer@example.com | H34: 042108662806 | I34: FAWFS7563Z | J34: ICIC0114988 | K34: 065846425232 | L34: MH/6264676 | M34: 42203648760561978 | N34: P | O34: P | P34: P | Q34: P | R34: P | S34: P | T34: WO | U34: P | V34: P | W34: P | X34: P | Y34: P | Z34: P | AA34: WO | AB34: P | AC34: P | AD34: P | AE34: P | AF34: P | AG34: P | AH34: WO | AI34: P | AJ34: P | AK34: A | AL34: P | AM34: P | AN34: P | AO34: WO | AP34: P | AQ34: P | AR34: =COUNTIF(N34:AQ34,"P") -> 25 | AS34: =COUNTIF(N34:AQ34,"A") -> 1 | AT34: =COUNTIF(N34:AQ34,"HO") -> 0 | AU34: =COUNTIF(N34:AQ34,"L") -> 0 | AV34: =COUNTIF(N34:AQ34,"WO") -> 4 | AW34: =COUNTIF(N34:AQ34,"H") -> 0 | AX34: =SUM(AR34:AW34)-AS34-IF(AU34>1,AU34-1,0)-(AT34/2)-AV34 -> 25 | AY34: 16000 | AZ34: =AY34/30*AX34 -> 13333.333 | BA34: =AZ34*20% -> 2666.6667 | BB34: =AZ34*40% -> 5333.3333 | BC34: =5000/30*AX34 -> 4166.6667 | BD34: =VLOOKUP(A34,[1]Sheet3!$A$2:$D$52,4,0) -> #N/A | BE34: =SUM(AZ34:BD34) -> #N/A | BF34: =IF(SUM(AZ34:BA34)>=15000,1800,SUM(AZ34:BA34)*12%) -> 1800 | BG34: =BE34*0.75% -> #N/A | BH34: =IF(SUM(AZ34:BA34)>=15000,550.5,(SUM(AZ34:BA34)*3.67%)) -> 550.5 | BI34: =IF(SUM(AZ34:BA34)>=15000,1249.5,SUM(AZ34:BA34)*8.33%) -> 1249.5 | BJ34: =IF(BE34>=21000,0,BE34*3.25%) -> #N/A | BK34: =IF(BE34>25000,200,IF(BE34>20000,150,IF(BE34>15000,100,0))) -> #N/A | BL34: =IF((BE34*12)<=400000,0, IF((BE34*12)<=800000,((BE34*12)-400000)*5%, IF((BE34*12)<=1200000,20000+((BE34*12)-800000)*10%, IF((BE34*12)<=1600000,60000+((BE34*12)-1200000)*15%, IF((BE34*12)<=2000000,120000+((BE34*12)-1600000)*20%, IF((BE34*12)<=2400000,200000+((BE34*12)-2000000)*25%, IF((BE34*12)>2400000,300000+((BE34*12)-2400000)*30%)))))))/12 -> #N/A | BM34: 0 | BN34: =BE34-BF34-BG34-BH34-BI34-BJ34-BK34-BL34-BM34 -> #N/A
A35: EMP032 | B35: Rajesh Reddy | C35: Engineer | D35: Admin | E35: 04-07-2023 | F35: 9799206097 | G35: rajesh.reddy@example.com | H35: 989521749163 | I35: THQGR2632N | J35: HDFC0715796 | K35: 516437934079 | L35: MH/3938127 | M35: 76530270745003163 | N35: HO | O35: P | P35: P | Q35: P | R35: P | S35: P | T35: WO | U35: P | V35: P | W35: P | X35: P | Y35: P | Z35: P | AA35: WO | AB35: P | AC35: P | AD35: P | AE35: P | AF35: P | AG35: P | AH35: WO | AI35: P | AJ35: P | AK35: P | AL35: A | AM35: P | AN35: P | AO35: WO | AP35: P | AQ35: P | AR35: =COUNTIF(N35:AQ35,"P") -> 24 | AS35: =COUNTIF(N35:AQ35,"A") -> 1 | AT35: =COUNTIF(N35:AQ35,"HO") -> 1 | AU35: =COUNTIF(N35:AQ35,"L") -> 0 | AV35: =COUNTIF(N35:AQ35,"WO") -> 4 | AW35: =COUNTIF(N35:AQ35,"H") -> 0 | AX35: =SUM(AR35:AW35)-AS35-IF(AU35>1,AU35-1,0)-(AT35/2)-AV35 -> 24.5 | AY35: 29000 | AZ35: =AY35/30*AX35 -> 23683.333 | BA35: =AZ35*20% -> 4736.6667 | BB35: =AZ35*40% -> 9473.3333 | BC35: =5000/30*AX35 -> 4083.3333 | BD35: =VLOOKUP(A35,[1]Sheet3!$A$2:$D$52,4,0) -> #N/A | BE35: =SUM(AZ35:BD35) -> #N/A | BF35: =IF(SUM(AZ35:BA35)>=15000,1800,SUM(AZ35:BA35)*12%) -> 1800 | BG35: =BE35*0.75% -> #N/A | BH35: =IF(SUM(AZ35:BA35)>=15000,550.5,(SUM(AZ35:BA35)*3.67%)) -> 550.5 | BI35: =IF(SUM(AZ35:BA35)>=15000,1249.5,SUM(AZ35:BA35)*8.33%) -> 1249.5 | BJ35: =IF(BE35>=21000,0,BE35*3.25%) -> #N/A | BK35: =IF(BE35>25000,200,IF(BE35>20000,150,IF(BE35>15000,100,0))) -> #N/A | BL35: =IF((BE35*12)<=400000,0, IF((BE35*12)<=800000,((BE35*12)-400000)*5%, IF((BE35*12)<=1200000,20000+((BE35*12)-800000)*10%, IF((BE35*12)<=1600000,60000+((BE35*12)-1200000)*15%, IF((BE35*12)<=2000000,120000+((BE35*12)-1600000)*20%, IF((BE35*12)<=2400000,200000+((BE35*12)-2000000)*25%, IF((BE35*12)>2400000,300000+((BE35*12)-2400000)*30%)))))))/12 -> #N/A | BM35: 0 | BN35: =BE35-BF35-BG35-BH35-BI35-BJ35-BK35-BL35-BM35 -> #N/A
A36: EMP033 | B36: Praveen Das | C36: Assistant | D36: Operations | E36: 09-06-2018 | F36: 9089683762 | G36: praveen.das@example.com | H36: 916537683451 | I36: CSFCA2170X | J36: PUNB0078398 | K36: 536209084939 | L36: MH/5242728 | M36: 64499375434125945 | N36: P | O36: P | P36: P | Q36: P | R36: P | S36: P | T36: WO | U36: P | V36: P | W36: P | X36: P | Y36: P | Z36: P | AA36: WO | AB36: P | AC36: P | AD36: P | AE36: P | AF36: P | AG36: P | AH36: WO | AI36: P | AJ36: P | AK36: P | AL36: A | AM36: A | AN36: P | AO36: WO | AP36: P | AQ36: P | AR36: =COUNTIF(N36:AQ36,"P") -> 24 | AS36: =COUNTIF(N36:AQ36,"A") -> 2 | AT36: =COUNTIF(N36:AQ36,"HO") -> 0 | AU36: =COUNTIF(N36:AQ36,"L") -> 0 | AV36: =COUNTIF(N36:AQ36,"WO") -> 4 | AW36: =COUNTIF(N36:AQ36,"H") -> 0 | AX36: =SUM(AR36:AW36)-AS36-IF(AU36>1,AU36-1,0)-(AT36/2)-AV36 -> 24 | AY36: 14000 | AZ36: =AY36/30*AX36 -> 11200 | BA36: =AZ36*20% -> 2240 | BB36: =AZ36*40% -> 4480 | BC36: =5000/30*AX36 -> 4000 | BD36: =VLOOKUP(A36,[1]Sheet3!$A$2:$D$52,4,0) -> #N/A | BE36: =SUM(AZ36:BD36) -> #N/A | BF36: =IF(SUM(AZ36:BA36)>=15000,1800,SUM(AZ36:BA36)*12%) -> 1612.8 | BG36: =BE36*0.75% -> #N/A | BH36: =IF(SUM(AZ36:BA36)>=15000,550.5,(SUM(AZ36:BA36)*3.67%)) -> 493.248 | BI36: =IF(SUM(AZ36:BA36)>=15000,1249.5,SUM(AZ36:BA36)*8.33%) -> 1119.552 | BJ36: =IF(BE36>=21000,0,BE36*3.25%) -> #N/A | BK36: =IF(BE36>25000,200,IF(BE36>20000,150,IF(BE36>15000,100,0))) -> #N/A | BL36: =IF((BE36*12)<=400000,0, IF((BE36*12)<=800000,((BE36*12)-400000)*5%, IF((BE36*12)<=1200000,20000+((BE36*12)-800000)*10%, IF((BE36*12)<=1600000,60000+((BE36*12)-1200000)*15%, IF((BE36*12)<=2000000,120000+((BE36*12)-1600000)*20%, IF((BE36*12)<=2400000,200000+((BE36*12)-2000000)*25%, IF((BE36*12)>2400000,300000+((BE36*12)-2400000)*30%)))))))/12 -> #N/A | BM36: 0 | BN36: =BE36-BF36-BG36-BH36-BI36-BJ36-BK36-BL36-BM36 -> #N/A
A37: EMP034 | B37: Gaurav Sharma | C37: Manager | D37: Admin | E37: 18-04-2024 | F37: 9511527905 | G37: gaurav.sharma@example.com | H37: 933204052352 | I37: FKUHY5100Z | J37: PUNB0845568 | K37: 258861580821 | L37: MH/5951629 | M37: 33229599408536076 | N37: P | O37: P | P37: P | Q37: P | R37: P | S37: P | T37: WO | U37: P | V37: P | W37: P | X37: P | Y37: P | Z37: P | AA37: WO | AB37: P | AC37: P | AD37: P | AE37: P | AF37: P | AG37: P | AH37: WO | AI37: P | AJ37: P | AK37: P | AL37: P | AM37: P | AN37: P | AO37: WO | AP37: P | AQ37: P | AR37: =COUNTIF(N37:AQ37,"P") -> 26 | AS37: =COUNTIF(N37:AQ37,"A") -> 0 | AT37: =COUNTIF(N37:AQ37,"HO") -> 0 | AU37: =COUNTIF(N37:AQ37,"L") -> 0 | AV37: =COUNTIF(N37:AQ37,"WO") -> 4 | AW37: =COUNTIF(N37:AQ37,"H") -> 0 | AX37: =SUM(AR37:AW37)-AS37-IF(AU37>1,AU37-1,0)-(AT37/2)-AV37 -> 26 | AY37: 13000 | AZ37: =AY37/30*AX37 -> 11266.667 | BA37: =AZ37*20% -> 2253.3333 | BB37: =AZ37*40% -> 4506.6667 | BC37: =5000/30*AX37 -> 4333.3333 | BD37: =VLOOKUP(A37,[1]Sheet3!$A$2:$D$52,4,0) -> #N/A | BE37: =SUM(AZ37:BD37) -> #N/A | BF37: =IF(SUM(AZ37:BA37)>=15000,1800,SUM(AZ37:BA37)*12%) -> 1622.4 | BG37: =BE37*0.75% -> #N/A | BH37: =IF(SUM(AZ37:BA37)>=15000,550.5,(SUM(AZ37:BA37)*3.67%)) -> 496.184 | BI37: =IF(SUM(AZ37:BA37)>=15000,1249.5,SUM(AZ37:BA37)*8.33%) -> 1126.216 | BJ37: =IF(BE37>=21000,0,BE37*3.25%) -> #N/A | BK37: =IF(BE37>25000,200,IF(BE37>20000,150,IF(BE37>15000,100,0))) -> #N/A | BL37: =IF((BE37*12)<=400000,0, IF((BE37*12)<=800000,((BE37*12)-400000)*5%, IF((BE37*12)<=1200000,20000+((BE37*12)-800000)*10%, IF((BE37*12)<=1600000,60000+((BE37*12)-1200000)*15%, IF((BE37*12)<=2000000,120000+((BE37*12)-1600000)*20%, IF((BE37*12)<=2400000,200000+((BE37*12)-2000000)*25%, IF((BE37*12)>2400000,300000+((BE37*12)-2400000)*30%)))))))/12 -> #N/A | BM37: 0 | BN37: =BE37-BF37-BG37-BH37-BI37-BJ37-BK37-BL37-BM37 -> #N/A
A38: EMP035 | B38: Lokesh Jain | C38: Manager | D38: IT | E38: 20-01-2015 | F38: 9289897296 | G38: lokesh.jain@example.com | H38: 783878808193 | I38: DUXXG5278M | J38: SBIN0033516 | K38: 511857366591 | L38: MH/1875218 | M38: 98164964401217531 | N38: P | O38: P | P38: P | Q38: P | R38: P | S38: P | T38: WO | U38: P | V38: P | W38: P | X38: P | Y38: P | Z38: P | AA38: WO | AB38: P | AC38: P | AD38: P | AE38: P | AF38: P | AG38: P | AH38: WO | AI38: P | AJ38: P | AK38: P | AL38: P | AM38: A | AN38: P | AO38: WO | AP38: P | AQ38: P | AR38: =COUNTIF(N38:AQ38,"P") -> 25 | AS38: =COUNTIF(N38:AQ38,"A") -> 1 | AT38: =COUNTIF(N38:AQ38,"HO") -> 0 | AU38: =COUNTIF(N38:AQ38,"L") -> 0 | AV38: =COUNTIF(N38:AQ38,"WO") -> 4 | AW38: =COUNTIF(N38:AQ38,"H") -> 0 | AX38: =SUM(AR38:AW38)-AS38-IF(AU38>1,AU38-1,0)-(AT38/2)-AV38 -> 25 | AY38: 12000 | AZ38: =AY38/30*AX38 -> 10000 | BA38: =AZ38*20% -> 2000 | BB38: =AZ38*40% -> 4000 | BC38: =5000/30*AX38 -> 4166.6667 | BD38: =VLOOKUP(A38,[1]Sheet3!$A$2:$D$52,4,0) -> #N/A | BE38: =SUM(AZ38:BD38) -> #N/A | BF38: =IF(SUM(AZ38:BA38)>=15000,1800,SUM(AZ38:BA38)*12%) -> 1440 | BG38: =BE38*0.75% -> #N/A | BH38: =IF(SUM(AZ38:BA38)>=15000,550.5,(SUM(AZ38:BA38)*3.67%)) -> 440.4 | BI38: =IF(SUM(AZ38:BA38)>=15000,1249.5,SUM(AZ38:BA38)*8.33%) -> 999.6 | BJ38: =IF(BE38>=21000,0,BE38*3.25%) -> #N/A | BK38: =IF(BE38>25000,200,IF(BE38>20000,150,IF(BE38>15000,100,0))) -> #N/A | BL38: =IF((BE38*12)<=400000,0, IF((BE38*12)<=800000,((BE38*12)-400000)*5%, IF((BE38*12)<=1200000,20000+((BE38*12)-800000)*10%, IF((BE38*12)<=1600000,60000+((BE38*12)-1200000)*15%, IF((BE38*12)<=2000000,120000+((BE38*12)-1600000)*20%, IF((BE38*12)<=2400000,200000+((BE38*12)-2000000)*25%, IF((BE38*12)>2400000,300000+((BE38*12)-2400000)*30%)))))))/12 -> #N/A | BM38: 0 | BN38: =BE38-BF38-BG38-BH38-BI38-BJ38-BK38-BL38-BM38 -> #N/A
A39: EMP036 | B39: Kiran Nair | C39: Analyst | D39: Marketing | E39: 17-05-2024 | F39: 9502301608 | G39: kiran.nair@example.com | H39: 268488738870 | I39: FFIVG7744V | J39: HDFC0898784 | K39: 749613703644 | L39: MH/5833369 | M39: 15010322640301459 | N39: P | O39: P | P39: P | Q39: P | R39: P | S39: P | T39: WO | U39: P | V39: P | W39: P | X39: P | Y39: P | Z39: P | AA39: WO | AB39: P | AC39: P | AD39: P | AE39: P | AF39: P | AG39: P | AH39: WO | AI39: P | AJ39: P | AK39: P | AL39: P | AM39: A | AN39: P | AO39: WO | AP39: P | AQ39: P | AR39: =COUNTIF(N39:AQ39,"P") -> 25 | AS39: =COUNTIF(N39:AQ39,"A") -> 1 | AT39: =COUNTIF(N39:AQ39,"HO") -> 0 | AU39: =COUNTIF(N39:AQ39,"L") -> 0 | AV39: =COUNTIF(N39:AQ39,"WO") -> 4 | AW39: =COUNTIF(N39:AQ39,"H") -> 0 | AX39: =SUM(AR39:AW39)-AS39-IF(AU39>1,AU39-1,0)-(AT39/2)-AV39 -> 25 | AY39: 32654 | AZ39: =AY39/30*AX39 -> 27211.667 | BA39: =AZ39*20% -> 5442.3333 | BB39: =AZ39*40% -> 10884.667 | BC39: =5000/30*AX39 -> 4166.6667 | BD39: =VLOOKUP(A39,[1]Sheet3!$A$2:$D$52,4,0) -> #N/A | BE39: =SUM(AZ39:BD39) -> #N/A | BF39: =IF(SUM(AZ39:BA39)>=15000,1800,SUM(AZ39:BA39)*12%) -> 1800 | BG39: =BE39*0.75% -> #N/A | BH39: =IF(SUM(AZ39:BA39)>=15000,550.5,(SUM(AZ39:BA39)*3.67%)) -> 550.5 | BI39: =IF(SUM(AZ39:BA39)>=15000,1249.5,SUM(AZ39:BA39)*8.33%) -> 1249.5 | BJ39: =IF(BE39>=21000,0,BE39*3.25%) -> #N/A | BK39: =IF(BE39>25000,200,IF(BE39>20000,150,IF(BE39>15000,100,0))) -> #N/A | BL39: =IF((BE39*12)<=400000,0, IF((BE39*12)<=800000,((BE39*12)-400000)*5%, IF((BE39*12)<=1200000,20000+((BE39*12)-800000)*10%, IF((BE39*12)<=1600000,60000+((BE39*12)-1200000)*15%, IF((BE39*12)<=2000000,120000+((BE39*12)-1600000)*20%, IF((BE39*12)<=2400000,200000+((BE39*12)-2000000)*25%, IF((BE39*12)>2400000,300000+((BE39*12)-2400000)*30%)))))))/12 -> #N/A | BM39: 0 | BN39: =BE39-BF39-BG39-BH39-BI39-BJ39-BK39-BL39-BM39 -> #N/A
... A53: EMP050 | B53: Sunil Bansal | C53: Analyst | D53: Marketing | E53: 21-02-2025 | F53: 9703857290 | G53: sunil.bansal@example.com | H53: 068051784984 | I53: SRVUZ3314X | J53: PUNB0496505 | K53: 056336636302 | L53: MH/0222525 | M53: 00008676143634894 | N53: P | O53: P | P53: P | Q53: P | R53: P | S53: P | T53: WO | U53: P | V53: P | W53: P | X53: P | Y53: P | Z53: P | AA53: WO | AB53: P | AC53: P | AD53: P | AE53: P | AF53: P | AG53: P | AH53: WO | AI53: P | AJ53: P | AK53: P | AL53: P | AM53: P | AN53: P | AO53: WO | AP53: P | AQ53: P | AR53: =COUNTIF(N53:AQ53,"P") -> 26 | AS53: =COUNTIF(N53:AQ53,"A") -> 0 | AT53: =COUNTIF(N53:AQ53,"HO") -> 0 | AU53: =COUNTIF(N53:AQ53,"L") -> 0 | AV53: =COUNTIF(N53:AQ53,"WO") -> 4 | AW53: =COUNTIF(N53:AQ53,"H") -> 0 | AX53: =SUM(AR53:AW53)-AS53-IF(AU53>1,AU53-1,0)-(AT53/2)-AV53 -> 26 | AY53: 13000 | AZ53: =AY53/30*AX53 -> 11266.667 | BA53: =AZ53*20% -> 2253.3333 | BB53: =AZ53*40% -> 4506.6667 | BC53: =5000/30*AX53 -> 4333.3333 | BD53: =VLOOKUP(A53,[1]Sheet3!$A$2:$D$52,4,0) -> #N/A | BE53: =SUM(AZ53:BD53) -> #N/A | BF53: =IF(SUM(AZ53:BA53)>=15000,1800,SUM(AZ53:BA53)*12%) -> 1622.4 | BG53: =BE53*0.75% -> #N/A | BH53: =IF(SUM(AZ53:BA53)>=15000,550.5,(SUM(AZ53:BA53)*3.67%)) -> 496.184 | BI53: =IF(SUM(AZ53:BA53)>=15000,1249.5,SUM(AZ53:BA53)*8.33%) -> 1126.216 | BJ53: =IF(BE53>=21000,0,BE53*3.25%) -> #N/A | BK53: =IF(BE53>25000,200,IF(BE53>20000,150,IF(BE53>15000,100,0))) -> #N/A | BL53: =IF((BE53*12)<=400000,0, IF((BE53*12)<=800000,((BE53*12)-400000)*5%, IF((BE53*12)<=1200000,20000+((BE53*12)-800000)*10%, IF((BE53*12)<=1600000,60000+((BE53*12)-1200000)*15%, IF((BE53*12)<=2000000,120000+((BE53*12)-1600000)*20%, IF((BE53*12)<=2400000,200000+((BE53*12)-2000000)*25%, IF((BE53*12)>2400000,300000+((BE53*12)-2400000)*30%)))))))/12 -> #N/A | BM53: 0 | BN53: =BE53-BF53-BG53-BH53-BI53-BJ53-BK53-BL53-BM53 -> #N/A

Sheet Sheet1
C3: Dizital Mantras
C4: PaySlip of Sep 2025
C6: EMP ID | D6: EMP009 | E6: IFSC NO | F6: =IFERROR(VLOOKUP($D$6,Sheet2!$A$3:$BN$53,10,0),"") -> PUNB0581791
C7: Name | D7: =IFERROR(VLOOKUP($D$6,Sheet2!$A$3:$BN$53,2,0),"") -> Krishna Das | E7: EPF No | F7: =IFERROR(VLOOKUP($D$6,Sheet2!$A$3:$BN$53,12,0),"") -> MH/3408089
C8: Desgination | D8: =IFERROR(VLOOKUP($D$6,Sheet2!$A$3:$BN$53,3,0),"") -> Assistant | E8: Account No | F8: =IFERROR(VLOOKUP($D$6,Sheet2!$A$3:$BN$53,11,0),"") -> 338531694105
C9: Department | D9: =IFERROR(VLOOKUP($D$6,Sheet2!$A$3:$BN$53,4,0),"") -> Finance | E9: ESI No | F9: =IFERROR(VLOOKUP($D$6,Sheet2!$A$3:$BN$53,13,0),"") -> 21363270435774555
C10: Pan No | D10: =IFERROR(VLOOKUP($D$6,Sheet2!$A$3:$BN$53,9,0),"") -> TJNVS8878M | E10: Adhar No | F10: =IFERROR(VLOOKUP($D$6,Sheet2!$A$3:$BN$53,8,0),"") -> 210188000274
C11: Joining Date | D11: =IFERROR(VLOOKUP($D$6,Sheet2!$A$3:$BN$53,5,0),"") -> 30-08-2021 | E11: Payable Date | F11: =IFERROR(VLOOKUP($D$6,Sheet2!$A$3:$BN$53,50,0),"") -> 21.5
C12: Earnings Deductions
C13: Basic | D13: =IFERROR(VLOOKUP($D$6,Sheet2!$A$3:$BN$53,52,0),"") -> 11466.667 | E13: EPF 12% | F13: =IFERROR(VLOOKUP($D$6,Sheet2!$A$3:$BN$53,58,0),"") -> 1651.2
C14: DA | D14: =IFERROR(VLOOKUP($D$6,Sheet2!$A$3:$BN$53,53,0),"") -> 2293.3333 | E14: ESI 0.75% | F14: =IFERROR(VLOOKUP($D$6,Sheet2!$A$3:$BN$53,59,0),"")
C15: HRA | D15: =IFERROR(VLOOKUP($D$6,Sheet2!$A$3:$BN$53,54,0),"") -> 4586.6667 | E15: PT | F15: =IFERROR(VLOOKUP($D$6,Sheet2!$A$3:$BN$53,63,0),"")
C16: TA | D16: =IFERROR(VLOOKUP($D$6,Sheet2!$A$3:$BN$53,55,0),"") -> 3583.3333 | E16: TDS | F16: =IFERROR(VLOOKUP($D$6,Sheet2!$A$3:$BN$53,64,0),"")
C17: Incentive | D17: =IFERROR(VLOOKUP($D$6,Sheet2!$A$3:$BN$53,56,0),"") | E17: Advance | F17: =IFERROR(VLOOKUP($D$6,Sheet2!$A$3:$BN$53,65,0),"") -> 0
C19: Gross Salary | D19: =IFERROR(VLOOKUP($D$6,Sheet2!$A$3:$BN$53,57,0),"") | E19: Total Deduction | F19: =IF(SUM(F13:F17)=0,"",SUM(F13:F17)) -> 1651.2
C20: Net Salary | F20: =IFERROR(VLOOKUP($D$6,Sheet2!$A$3:$BN$53,66,0),"")
